Workbook

Sheet Burn Rate
A1: Quarterly cash burn rate: latest periodic filing per company
A2: Burn = net cash used in operating activities, from each company's latest 10-Q or interim 6-K. $ in thousands (ADXN in CHF thousands). Data retrieved 2026-10-03 from SEC EDGAR. Positive = cash consumed.
A4: Ticker | B4: Company | C4: Position ($K) | D4: Burn Rate ($K / qtr) | E4: Latest discrete qtr burn ($K) | F4: Currency | G4: Burn Rate in USD ($K / qtr) | H4: Period behind Burn Rate | I4: Position ties to filing cash? | J4: Flag
A5: ADXN | B5: Addex Therapeutics | C5: 767 | D5: =Detail!N5 -> 617.051 | E5: =Detail!T5 -> n/a | F5: =Detail!K5 -> CHF | G5: =Detail!Y5 -> 784.04737 | H5: H1 2026 (Jan-Jun) / 2 - 6-K | I5: =IF(ROUND(Detail!W5,0)=C5,"Yes","No") -> Yes | J5: Reports in Swiss francs (CHF). Your Position of 767 is CHF 767K, not USD. Semi-annual reporter, so burn = H1 / 2. After period end, raised USD 2.8M gross via its ATM (6-K, 2026-08-26).
A6: AEON | B6: Aeon Biopharma | C6: 3431 | D6: =Detail!N6 -> 3167 | E6: =Detail!T6 -> 3698 | F6: =Detail!K6 -> USD | G6: =Detail!Y6 -> 3167 | H6: H1 2026 (Jan-Jun) / 2 - 10-Q | I6: =IF(ROUND(Detail!W6,0)=C6,"Yes","No") -> Yes
A7: ATCX | B7: Atlas Critical Minerals Corporation | C7: 5536 | D7: =Detail!N7 -> 1612.3895 | E7: =Detail!T7 -> n/a | F7: =Detail!K7 -> USD | G7: =Detail!Y7 -> 1612.3895 | H7: H1 2026 (Jan-Jun) / 2 - 6-K | I7: =IF(ROUND(Detail!W7,0)=C7,"Yes","No") -> Yes | J7: Files 20-F/6-K (not 10-Q). Semi-annual, so burn = H1 / 2. Excludes $190,876 of capital-asset purchases (investing).
A8: CDIO | B8: Cardio Diagnostics Holdings | C8: 5587 | D8: =Detail!N8 -> 1452.288 | E8: =Detail!T8 -> 1342.364 | F8: =Detail!K8 -> USD | G8: =Detail!Y8 -> 1452.288 | H8: H1 2026 (Jan-Jun) / 2 - 10-Q | I8: =IF(ROUND(Detail!W8,0)=C8,"Yes","No") -> Yes | J8: Excludes $110,485 of H1 investing outflows (patent costs and equipment).
A9: EVGN | B9: Evogene | C9: 9316 | D9: =Detail!N9 -> 2464 | E9: =Detail!T9 -> 1974 | F9: =Detail!K9 -> USD | G9: =Detail!Y9 -> 2464 | H9: H1 2026 (Jan-Jun) / 2 - 6-K | I9: =IF(ROUND(Detail!W9,0)=C9,"Yes","No") -> Yes | J9: Total includes discontinued operations ($300K in H1; continuing operations alone = $4,628K). The Q2 release separately cites ~$2.1M of Q2 "consolidated cash usage" (company definition) and 2026 burn guidance of ~$8.5-9.5M.
A10: INTZ | B10: Intrusion | C10: 182 | D10: =Detail!N10 -> 2705.5 | E10: =Detail!T10 -> 3590 | F10: =Detail!K10 -> USD | G10: =Detail!Y10 -> 2705.5 | H10: H1 2026 (Jan-Jun) / 2 - 10-Q | I10: =IF(ROUND(Detail!W10,0)=C10,"Yes","No") -> Yes | J10: Q2 burn ($3,590K) is well above the H1 average. Excludes H1 capitalized software ($587K), equipment ($55K) and an acquisition ($356K).
A11: KAPA | B11: Kairos Pharma | C11: 2626 | D11: =Detail!N11 -> 1024 | E11: =Detail!T11 -> 1012 | F11: =Detail!K11 -> USD | G11: =Detail!Y11 -> 1024 | H11: H1 2026 (Jan-Jun) / 2 - 10-Q | I11: =IF(ROUND(Detail!W11,0)=C11,"Yes","No") -> Yes
A12: KPRX | B12: Kiora Pharmaceuticals | C12: 7077 | D12: =Detail!N12 -> 2526.6335 | E12: =Detail!T12 -> 1891.935 | F12: =Detail!K12 -> USD | G12: =Detail!Y12 -> 2526.6335 | H12: H1 2026 (Jan-Jun) / 2 - 10-Q | I12: =IF(ROUND(Detail!W12,0)=C12,"Yes","No") -> Yes | J12: Position excludes $9,761,994 of short-term investments also on the 6/30/26 balance sheet.
A13: LINK | B13: Interlink Electronics | C13: 1831 | D13: =Detail!N13 -> 414.5 | E13: =Detail!T13 -> 286 | F13: =Detail!K13 -> USD | G13: =Detail!Y13 -> 414.5 | H13: H1 2026 (Jan-Jun) / 2 - 10-Q | I13: =IF(ROUND(Detail!W13,0)=C13,"Yes","No") -> Yes
A14: MYND | B14: Mynd.ai | C14: 6820 | D14: =Detail!N14 -> 13220 | E14: =Detail!T14 -> n/a | F14: =Detail!K14 -> USD | G14: =Detail!Y14 -> 13220 | H14: H1 2026 (Jan-Jun) / 2 - 6-K | I14: =IF(ROUND(Detail!W14,0)=C14,"Yes","No") -> Yes | J14: Semi-annual, so burn = H1 / 2. The filing reports cash of $7,040K including $220K restricted; your 6,820 is net of restricted cash. Excludes $896K of H1 capex and capitalized software.
A15: NCEL | B15: NewcelX | C15: 710 | D15: =Detail!N15 -> 1436 | E15: =Detail!T15 -> n/a | F15: =Detail!K15 -> USD | G15: =Detail!Y15 -> 1436 | H15: H1 2026 (Jan-Jun) / 2 - 6-K | I15: =IF(ROUND(Detail!W15,0)=C15,"Yes","No") -> Yes | J15: Semi-annual, so burn = H1 / 2. Its filing reports ~$1.4M gross raised in a private placement after June 30, 2026.
A16: NSRX | B16: Nasus Pharma | C16: 7818 | D16: =Detail!N16 -> 3018 | E16: =Detail!T16 -> n/a | F16: =Detail!K16 -> USD | G16: =Detail!Y16 -> 3018 | H16: H1 2026 (Jan-Jun) / 2 - 6-K | I16: =IF(ROUND(Detail!W16,0)=C16,"Yes","No") -> Yes | J16: Semi-annual, so burn = H1 / 2. Total includes $41K of discontinued operations. Position excludes a $4,000K short-term deposit.
A17: NXXT | B17: NextNRG | C17: 884 | D17: =Detail!N17 -> 2283.803 | E17: =Detail!T17 -> 2418.715 | F17: =Detail!K17 -> USD | G17: =Detail!Y17 -> 2283.803 | H17: H1 2026 (Jan-Jun) / 2 - 10-Q | I17: =IF(ROUND(Detail!W17,0)=C17,"Yes","No") -> Yes
A18: ODYS | B18: Odysight.ai | C18: 17220 | D18: =Detail!N18 -> 4356.5 | E18: =Detail!T18 -> 4459 | F18: =Detail!K18 -> USD | G18: =Detail!Y18 -> 4356.5 | H18: H1 2026 (Jan-Jun) / 2 - 10-Q | I18: =IF(ROUND(Detail!W18,0)=C18,"Yes","No") -> Yes | J18: The 10-Q itself reports the Q2 three-month figure ($4,459K); it matches the subtraction.
A19: OPTT | B19: Ocean Power Technologies | C19: 7356 | D19: =Detail!N19 -> 10240 | E19: =Detail!T19 -> 10240 | F19: =Detail!K19 -> USD | G19: =Detail!Y19 -> 10240 | H19: Q1 FY27 (May-Jul 2026) - 10-Q | I19: =IF(ROUND(Detail!W19,0)=C19,"Yes","No") -> Yes | J19: Fiscal year ends April 30, so the latest quarter is May-Jul 2026 (one month later than the others). Prior-year same quarter: $5,605K.
A20: QNRX | B20: Quoin Pharmaceuticals | C20: 3846 | D20: =Detail!N20 -> 4006.6315 | E20: =Detail!T20 -> 3144.34 | F20: =Detail!K20 -> USD | G20: =Detail!Y20 -> 4006.6315 | H20: H1 2026 (Jan-Jun) / 2 - 10-Q | I20: =IF(ROUND(Detail!W20,0)=C20,"Yes","No") -> Yes | J20: Position excludes $6,954,476 of investments also on the 6/30/26 balance sheet.
A21: TPST | B21: Tempest Therapeutics | C21: 779 | D21: =Detail!N21 -> 5188.5 | E21: =Detail!T21 -> 2779 | F21: =Detail!K21 -> USD | G21: =Detail!Y21 -> 5188.5 | H21: H1 2026 (Jan-Jun) / 2 - 10-Q | I21: =IF(ROUND(Detail!W21,0)=C21,"Yes","No") -> Yes | J21: Q2 burn ($2,779K) is far below Q1 ($7,598K), so the H1 average overstates the current pace.
A22: WAVE | B22: Eco Wave Power Global AB | C22: 8152 | D22: =Detail!N22 -> 722 | E22: =Detail!T22 -> n/a | F22: =Detail!K22 -> USD | G22: =Detail!Y22 -> 722 | H22: H1 2026 (Jan-Jun) / 2 - 6-K | I22: =IF(ROUND(Detail!W22,0)=C22,"Yes","No") -> Yes | J22: Semi-annual, so burn = H1 / 2.
A24: Notes
A25: 1. Burn Rate = average quarterly burn over the latest filing's year-to-date period (10-Q filers: Jan-Jun / 2; OPTT: its single May-Jul quarter; 6-K filers: H1 / 2). It uses only the latest filing, as requested.
A26: 2. Latest discrete qtr = the most recent three months alone: latest 10-Q YTD minus the Q1 10-Q, or a three-month figure the company published (EVGN, ODYS). "n/a" = the company does not publish quarterly cash flows.
A27: 3. ADXN reports in Swiss francs. Its Position (767) and Burn Rate are CHF thousands; the USD column converts at the H1-2026 average rate on the Inputs sheet.
A28: 4. Capex and capitalized costs are excluded (operating cash flow only). The Flag column notes where they are material.
A29: 5. Every figure traces to the SEC document on the Detail and Sources sheets.

Sheet Inputs
A1: Inputs and assumptions
A3: CHF to USD, H1-2026 average | B3: 1.2706362 | C3: Simple average of 128 weekday closing rates, 2026-01-02 to 2026-06-30 (weekday closes). Source: Financial Modeling Prep (FMP) forex historical EOD, symbol CHFUSD, retrieved 2026-10-03. Used only to translate Addex's CHF burn into USD.
A4: CHF to USD at 2026-06-30 | B4: 1.2371 | C4: Closing rate on 2026-06-30. Source: Financial Modeling Prep (FMP) forex historical EOD, symbol CHFUSD, retrieved 2026-10-03. Used only to translate Addex's CHF cash into USD.
A5: USD to USD | B5: 1
A7: Data retrieved | B7: 2026-10-03 | C7: Date all SEC EDGAR documents and the FX series were pulled (system clock, UTC).
A9: Color key: blue = hard-coded input from a cited source; black = formula; green = link to another sheet; yellow fill = key assumption.

Sheet Detail
A1: Detail: as-reported operating cash flow and burn-rate calculations
A2: Burn rate = net cash used in operating activities. Avg quarterly burn = -(YTD operating cash flow) / (months in period / 3). Latest discrete quarter = latest YTD minus prior 10-Q YTD (or a three-month figure the company reported directly). Positive burn = cash consumed.
A4: Ticker | B4: Filer type | C4: Form / document | D4: Filed | E4: Period start | F4: Period end | G4: Months in period | H4: Operating cash flow line, exactly as labeled in filing | I4: Operating cash flow, as reported (filing units) | J4: Filing unit (1 = whole, 1000 = thousands) | K4: Currency | L4: Operating cash flow (000s) | M4: Quarters in period | N4: BURN RATE: avg quarterly burn (000s) | O4: Q1 YTD operating cash flow, as reported (prior 10-Q) | P4: Prior unit | Q4: Prior filing reference | R4: Discrete quarter operating cash flow reported directly (000s) | S4: Discrete-quarter source | T4: Latest discrete quarter burn (000s) | U4: Cash & equivalents line, as reported (filing units) | V4: Restricted cash included in that line | W4: Cash ex-restricted (000s) | X4: FX to USD | Y4: Burn rate in USD (000s) | Z4: Accession no. | AA4: Source document URL | AB4: Notes
A5: ADXN | B5: Foreign private issuer (semi-annual, 6-K) | C5: 6-K (Ex. 99.1 interim financial statements) | D5: 2026-09-28 | E5: 2026-01-01 | F5: 2026-06-30 | G5: 6 | H5: Net cash used in operating activities | I5: -1234102 | J5: 1 | K5: CHF | L5: =I5*J5/1000 -> -1234.102 | M5: =G5/3 -> 2 | N5: =-L5/M5 -> 617.051 | Q5: n/a: no Q1 10-Q (semi-annual/6-K filer) | T5: =IF(G5=3,-L5,IF(ISNUMBER(O5),-(L5-O5*P5/1000),IF(ISNUMBER(R5),-R5,"n/a"))) -> n/a | U5: 767328 | V5: 0 | W5: =(U5-V5)*J5/1000 -> 767.328 | X5: =Inputs!$B$3 -> 1.2706362 | Y5: =N5*X5 -> 784.04737 | Z5: 0001104659-26-111142 | AA5: https://www.sec.gov/Archives/edgar/data/1574232/000110465926111142/adxn-20260630xex99d1.htm | AB5: Reports in Swiss francs (CHF). Your Position of 767 is CHF 767K, not USD. Semi-annual reporter, so burn = H1 / 2. After period end, raised USD 2.8M gross via its ATM (6-K, 2026-08-26).
A6: AEON | B6: U.S. domestic filer (10-Q) | C6: 10-Q | D6: 2026-08-12 | E6: 2026-01-01 | F6: 2026-06-30 | G6: 6 | H6: Net cash used in operating activities | I6: -6334 | J6: 1000 | K6: USD | L6: =I6*J6/1000 -> -6334 | M6: =G6/3 -> 2 | N6: =-L6/M6 -> 3167 | O6: -2636 | P6: 1000 | Q6: 10-Q filed 2026-05-14, acc. 0001837607-26-000042 | T6: =IF(G6=3,-L6,IF(ISNUMBER(O6),-(L6-O6*P6/1000),IF(ISNUMBER(R6),-R6,"n/a"))) -> 3698 | U6: 3431 | V6: 0 | W6: =(U6-V6)*J6/1000 -> 3431 | X6: =Inputs!$B$5 -> 1 | Y6: =N6*X6 -> 3167 | Z6: 0001837607-26-000062 | AA6: https://www.sec.gov/Archives/edgar/data/1837607/000183760726000062/aeon-20260630x10q.htm
A7: ATCX | B7: Foreign private issuer (semi-annual, 6-K) | C7: 6-K (Ex. 99.1 interim financial statements) | D7: 2026-07-31 | E7: 2026-01-01 | F7: 2026-06-30 | G7: 6 | H7: Net cash provided by (used in) operating activities | I7: -3224779 | J7: 1 | K7: USD | L7: =I7*J7/1000 -> -3224.779 | M7: =G7/3 -> 2 | N7: =-L7/M7 -> 1612.3895 | Q7: n/a: no Q1 10-Q (semi-annual/6-K filer) | T7: =IF(G7=3,-L7,IF(ISNUMBER(O7),-(L7-O7*P7/1000),IF(ISNUMBER(R7),-R7,"n/a"))) -> n/a | U7: 5536422 | V7: 0 | W7: =(U7-V7)*J7/1000 -> 5536.422 | X7: =Inputs!$B$5 -> 1 | Y7: =N7*X7 -> 1612.3895 | Z7: 0001493152-26-035635 | AA7: https://www.sec.gov/Archives/edgar/data/1684688/000149315226035635/ex99-1.htm | AB7: Files 20-F/6-K (not 10-Q). Semi-annual, so burn = H1 / 2. Excludes $190,876 of capital-asset purchases (investing).
A8: CDIO | B8: U.S. domestic filer (10-Q) | C8: 10-Q | D8: 2026-08-07 | E8: 2026-01-01 | F8: 2026-06-30 | G8: 6 | H8: NET CASH USED IN OPERATING ACTIVITIES | I8: -2904576 | J8: 1 | K8: USD | L8: =I8*J8/1000 -> -2904.576 | M8: =G8/3 -> 2 | N8: =-L8/M8 -> 1452.288 | O8: -1562212 | P8: 1 | Q8: 10-Q filed 2026-05-15, acc. 0001553350-26-000089 | T8: =IF(G8=3,-L8,IF(ISNUMBER(O8),-(L8-O8*P8/1000),IF(ISNUMBER(R8),-R8,"n/a"))) -> 1342.364 | U8: 5586697 | V8: 0 | W8: =(U8-V8)*J8/1000 -> 5586.697 | X8: =Inputs!$B$5 -> 1 | Y8: =N8*X8 -> 1452.288 | Z8: 0001079973-26-001016 | AA8: https://www.sec.gov/Archives/edgar/data/1870144/000107997326001016/cdio_10q-063026.htm | AB8: Excludes $110,485 of H1 investing outflows (patent costs and equipment).
A9: EVGN | B9: Foreign private issuer (6-K) | C9: 6-K (Ex. 99.1 interim financial statements) | D9: 2026-09-28 | E9: 2026-01-01 | F9: 2026-06-30 | G9: 6 | H9: Net cash used in operating activities | I9: -4928 | J9: 1000 | K9: USD | L9: =I9*J9/1000 -> -4928 | M9: =G9/3 -> 2 | N9: =-L9/M9 -> 2464 | Q9: n/a: no Q1 10-Q (semi-annual/6-K filer) | R9: -1974 | S9: Q2-2026 results release, 6-K filed 2026-08-18, acc. 0001178913-26-004174 (Ex. 99.1), three months ended 2026-06-30 | T9: =IF(G9=3,-L9,IF(ISNUMBER(O9),-(L9-O9*P9/1000),IF(ISNUMBER(R9),-R9,"n/a"))) -> 1974 | U9: 9316 | V9: 0 | W9: =(U9-V9)*J9/1000 -> 9316 | X9: =Inputs!$B$5 -> 1 | Y9: =N9*X9 -> 2464 | Z9: 0001178913-26-004636 | AA9: https://www.sec.gov/Archives/edgar/data/1574565/000117891326004636/exhibit_99-1.htm | AB9: Total includes discontinued operations ($300K in H1; continuing operations alone = $4,628K). The Q2 release separately cites ~$2.1M of Q2 "consolidated cash usage" (company definition) and 2026 burn guidance of ~$8.5-9.5M.
A10: INTZ | B10: U.S. domestic filer (10-Q) | C10: 10-Q | D10: 2026-08-11 | E10: 2026-01-01 | F10: 2026-06-30 | G10: 6 | H10: Net cash used in operating activities | I10: -5411 | J10: 1000 | K10: USD | L10: =I10*J10/1000 -> -5411 | M10: =G10/3 -> 2 | N10: =-L10/M10 -> 2705.5 | O10: -1821 | P10: 1000 | Q10: 10-Q filed 2026-05-14, acc. 0001683168-26-003931 | T10: =IF(G10=3,-L10,IF(ISNUMBER(O10),-(L10-O10*P10/1000),IF(ISNUMBER(R10),-R10,"n/a"))) -> 3590 | U10: 182 | V10: 0 | W10: =(U10-V10)*J10/1000 -> 182 | X10: =Inputs!$B$5 -> 1 | Y10: =N10*X10 -> 2705.5 | Z10: 0001683168-26-006209 | AA10: https://www.sec.gov/Archives/edgar/data/736012/000168316826006209/intrusion_i10q-063026.htm | AB10: Q2 burn ($3,590K) is well above the H1 average. Excludes H1 capitalized software ($587K), equipment ($55K) and an acquisition ($356K).
A11: KAPA | B11: U.S. domestic filer (10-Q) | C11: 10-Q | D11: 2026-08-12 | E11: 2026-01-01 | F11: 2026-06-30 | G11: 6 | H11: Net cash used in operating activities | I11: -2048 | J11: 1000 | K11: USD | L11: =I11*J11/1000 -> -2048 | M11: =G11/3 -> 2 | N11: =-L11/M11 -> 1024 | O11: -1036 | P11: 1000 | Q11: 10-Q filed 2026-05-13, acc. 0001493152-26-022796 | T11: =IF(G11=3,-L11,IF(ISNUMBER(O11),-(L11-O11*P11/1000),IF(ISNUMBER(R11),-R11,"n/a"))) -> 1012 | U11: 2626 | V11: 0 | W11: =(U11-V11)*J11/1000 -> 2626 | X11: =Inputs!$B$5 -> 1 | Y11: =N11*X11 -> 1024 | Z11: 0001493152-26-037355 | AA11: https://www.sec.gov/Archives/edgar/data/1962011/000149315226037355/form10-q.htm
A12: KPRX | B12: U.S. domestic filer (10-Q) | C12: 10-Q | D12: 2026-08-07 | E12: 2026-01-01 | F12: 2026-06-30 | G12: 6 | H12: Net Cash Used in Operating Activities | I12: -5053267 | J12: 1 | K12: USD | L12: =I12*J12/1000 -> -5053.267 | M12: =G12/3 -> 2 | N12: =-L12/M12 -> 2526.6335 | O12: -3161332 | P12: 1 | Q12: 10-Q filed 2026-05-08, acc. 0001372514-26-000047 | T12: =IF(G12=3,-L12,IF(ISNUMBER(O12),-(L12-O12*P12/1000),IF(ISNUMBER(R12),-R12,"n/a"))) -> 1891.935 | U12: 7076533 | V12: 0 | W12: =(U12-V12)*J12/1000 -> 7076.533 | X12: =Inputs!$B$5 -> 1 | Y12: =N12*X12 -> 2526.6335 | Z12: 0001372514-26-000074 | AA12: https://www.sec.gov/Archives/edgar/data/1372514/000137251426000074/kprx-20260630.htm | AB12: Position excludes $9,761,994 of short-term investments also on the 6/30/26 balance sheet.
A13: LINK | B13: U.S. domestic filer (10-Q) | C13: 10-Q | D13: 2026-08-13 | E13: 2026-01-01 | F13: 2026-06-30 | G13: 6 | H13: Net cash (used in) operating activities | I13: -829 | J13: 1000 | K13: USD | L13: =I13*J13/1000 -> -829 | M13: =G13/3 -> 2 | N13: =-L13/M13 -> 414.5 | O13: -543 | P13: 1000 | Q13: 10-Q filed 2026-05-14, acc. 0001104659-26-061139 | T13: =IF(G13=3,-L13,IF(ISNUMBER(O13),-(L13-O13*P13/1000),IF(ISNUMBER(R13),-R13,"n/a"))) -> 286 | U13: 1831 | V13: 0 | W13: =(U13-V13)*J13/1000 -> 1831 | X13: =Inputs!$B$5 -> 1 | Y13: =N13*X13 -> 414.5 | Z13: 0001104659-26-096041 | AA13: https://www.sec.gov/Archives/edgar/data/828146/000110465926096041/link-20260630x10q.htm
A14: MYND | B14: Foreign private issuer (semi-annual, 6-K) | C14: 6-K (unaudited consolidated financial statements) | D14: 2026-08-27 | E14: 2026-01-01 | F14: 2026-06-30 | G14: 6 | H14: Net cash used in operating activities | I14: -26440 | J14: 1000 | K14: USD | L14: =I14*J14/1000 -> -26440 | M14: =G14/3 -> 2 | N14: =-L14/M14 -> 13220 | Q14: n/a: no Q1 10-Q (semi-annual/6-K filer) | T14: =IF(G14=3,-L14,IF(ISNUMBER(O14),-(L14-O14*P14/1000),IF(ISNUMBER(R14),-R14,"n/a"))) -> n/a | U14: 7040 | V14: 220 | W14: =(U14-V14)*J14/1000 -> 6820 | X14: =Inputs!$B$5 -> 1 | Y14: =N14*X14 -> 13220 | Z14: 0001708441-26-000102 | AA14: https://www.sec.gov/Archives/edgar/data/1708441/000170844126000102/mynd-20260630_d2.htm | AB14: Semi-annual, so burn = H1 / 2. The filing reports cash of $7,040K including $220K restricted; your 6,820 is net of restricted cash. Excludes $896K of H1 capex and capitalized software.
A15: NCEL | B15: Foreign private issuer (semi-annual, 6-K) | C15: 6-K (Ex. 99.1 interim financial statements) | D15: 2026-09-18 | E15: 2026-01-01 | F15: 2026-06-30 | G15: 6 | H15: Net cash provided by (used in) operating activities | I15: -2872 | J15: 1000 | K15: USD | L15: =I15*J15/1000 -> -2872 | M15: =G15/3 -> 2 | N15: =-L15/M15 -> 1436 | Q15: n/a: no Q1 10-Q (semi-annual/6-K filer) | T15: =IF(G15=3,-L15,IF(ISNUMBER(O15),-(L15-O15*P15/1000),IF(ISNUMBER(R15),-R15,"n/a"))) -> n/a | U15: 710 | V15: 0 | W15: =(U15-V15)*J15/1000 -> 710 | X15: =Inputs!$B$5 -> 1 | Y15: =N15*X15 -> 1436 | Z15: 0001213900-26-101419 | AA15: https://www.sec.gov/Archives/edgar/data/1783036/000121390026101419/ea030514101ex99-1.htm | AB15: Semi-annual, so burn = H1 / 2. Its filing reports ~$1.4M gross raised in a private placement after June 30, 2026.
A16: NSRX | B16: Foreign private issuer (semi-annual, 6-K) | C16: 6-K (Ex. 99.1 interim financial statements) | D16: 2026-08-17 | E16: 2026-01-01 | F16: 2026-06-30 | G16: 6 | H16: Net cash used in operating activities | I16: -6036 | J16: 1000 | K16: USD | L16: =I16*J16/1000 -> -6036 | M16: =G16/3 -> 2 | N16: =-L16/M16 -> 3018 | Q16: n/a: no Q1 10-Q (semi-annual/6-K filer) | T16: =IF(G16=3,-L16,IF(ISNUMBER(O16),-(L16-O16*P16/1000),IF(ISNUMBER(R16),-R16,"n/a"))) -> n/a | U16: 7818 | V16: 0 | W16: =(U16-V16)*J16/1000 -> 7818 | X16: =Inputs!$B$5 -> 1 | Y16: =N16*X16 -> 3018 | Z16: 0001493152-26-038651 | AA16: https://www.sec.gov/Archives/edgar/data/2029039/000149315226038651/ex99-1.htm | AB16: Semi-annual, so burn = H1 / 2. Total includes $41K of discontinued operations. Position excludes a $4,000K short-term deposit.
A17: NXXT | B17: U.S. domestic filer (10-Q) | C17: 10-Q | D17: 2026-08-13 | E17: 2026-01-01 | F17: 2026-06-30 | G17: 6 | H17: Net cash used in operating activities | I17: -4567606 | J17: 1 | K17: USD | L17: =I17*J17/1000 -> -4567.606 | M17: =G17/3 -> 2 | N17: =-L17/M17 -> 2283.803 | O17: -2148891 | P17: 1 | Q17: 10-Q filed 2026-05-15, acc. 0001493152-26-023768 | T17: =IF(G17=3,-L17,IF(ISNUMBER(O17),-(L17-O17*P17/1000),IF(ISNUMBER(R17),-R17,"n/a"))) -> 2418.715 | U17: 883696 | V17: 0 | W17: =(U17-V17)*J17/1000 -> 883.696 | X17: =Inputs!$B$5 -> 1 | Y17: =N17*X17 -> 2283.803 | Z17: 0001493152-26-037738 | AA17: https://www.sec.gov/Archives/edgar/data/1817004/000149315226037738/form10-q.htm
A18: ODYS | B18: U.S. domestic filer (10-Q) | C18: 10-Q | D18: 2026-08-13 | E18: 2026-01-01 | F18: 2026-06-30 | G18: 6 | H18: Net cash flows used in operating activities | I18: -8713 | J18: 1000 | K18: USD | L18: =I18*J18/1000 -> -8713 | M18: =G18/3 -> 2 | N18: =-L18/M18 -> 4356.5 | O18: -4254 | P18: 1000 | Q18: 10-Q filed 2026-05-14, acc. 0001493152-26-023100 | R18: -4459 | S18: Same 10-Q, three months ended 2026-06-30 column | T18: =IF(G18=3,-L18,IF(ISNUMBER(O18),-(L18-O18*P18/1000),IF(ISNUMBER(R18),-R18,"n/a"))) -> 4459 | U18: 17220 | V18: 0 | W18: =(U18-V18)*J18/1000 -> 17220 | X18: =Inputs!$B$5 -> 1 | Y18: =N18*X18 -> 4356.5 | Z18: 0001493152-26-037618 | AA18: https://www.sec.gov/Archives/edgar/data/1577445/000149315226037618/form10-q.htm | AB18: The 10-Q itself reports the Q2 three-month figure ($4,459K); it matches the subtraction.
A19: OPTT | B19: U.S. domestic filer (10-Q) | C19: 10-Q (Q1 of FY ending 4/30/2027) | D19: 2026-09-14 | E19: 2026-05-01 | F19: 2026-07-31 | G19: 3 | H19: Net cash used in operating activities | I19: -10240 | J19: 1000 | K19: USD | L19: =I19*J19/1000 -> -10240 | M19: =G19/3 -> 1 | N19: =-L19/M19 -> 10240 | Q19: n/a: period is a single quarter | T19: =IF(G19=3,-L19,IF(ISNUMBER(O19),-(L19-O19*P19/1000),IF(ISNUMBER(R19),-R19,"n/a"))) -> 10240 | U19: 7356 | V19: 0 | W19: =(U19-V19)*J19/1000 -> 7356 | X19: =Inputs!$B$5 -> 1 | Y19: =N19*X19 -> 10240 | Z19: 0001493152-26-042579 | AA19: https://www.sec.gov/Archives/edgar/data/1378140/000149315226042579/form10-q.htm | AB19: Fiscal year ends April 30, so the latest quarter is May-Jul 2026 (one month later than the others). Prior-year same quarter: $5,605K.
A20: QNRX | B20: U.S. domestic filer (10-Q) | C20: 10-Q | D20: 2026-08-14 | E20: 2026-01-01 | F20: 2026-06-30 | G20: 6 | H20: Net cash used in operating activities | I20: -8013263 | J20: 1 | K20: USD | L20: =I20*J20/1000 -> -8013.263 | M20: =G20/3 -> 2 | N20: =-L20/M20 -> 4006.6315 | O20: -4868923 | P20: 1 | Q20: 10-Q filed 2026-05-07, acc. 0001104659-26-056941 | T20: =IF(G20=3,-L20,IF(ISNUMBER(O20),-(L20-O20*P20/1000),IF(ISNUMBER(R20),-R20,"n/a"))) -> 3144.34 | U20: 3845606 | V20: 0 | W20: =(U20-V20)*J20/1000 -> 3845.606 | X20: =Inputs!$B$5 -> 1 | Y20: =N20*X20 -> 4006.6315 | Z20: 0001104659-26-097064 | AA20: https://www.sec.gov/Archives/edgar/data/1671502/000110465926097064/qnrx-20260630x10q.htm | AB20: Position excludes $6,954,476 of investments also on the 6/30/26 balance sheet.
A21: TPST | B21: U.S. domestic filer (10-Q) | C21: 10-Q | D21: 2026-08-13 | E21: 2026-01-01 | F21: 2026-06-30 | G21: 6 | H21: Cash used in operating activities | I21: -10377 | J21: 1000 | K21: USD | L21: =I21*J21/1000 -> -10377 | M21: =G21/3 -> 2 | N21: =-L21/M21 -> 5188.5 | O21: -7598 | P21: 1000 | Q21: 10-Q filed 2026-05-14, acc. 0001193125-26-224289 | T21: =IF(G21=3,-L21,IF(ISNUMBER(O21),-(L21-O21*P21/1000),IF(ISNUMBER(R21),-R21,"n/a"))) -> 2779 | U21: 779 | V21: 0 | W21: =(U21-V21)*J21/1000 -> 779 | X21: =Inputs!$B$5 -> 1 | Y21: =N21*X21 -> 5188.5 | Z21: 0001193125-26-349381 | AA21: https://www.sec.gov/Archives/edgar/data/1544227/000119312526349381/tpst-20260630.htm | AB21: Q2 burn ($2,779K) is far below Q1 ($7,598K), so the H1 average overstates the current pace.
A22: WAVE | B22: Foreign private issuer (semi-annual, 6-K) | C22: 6-K (Ex. 99.1 interim financial statements) | D22: 2026-08-11 | E22: 2026-01-01 | F22: 2026-06-30 | G22: 6 | H22: Net cash used in operating activities | I22: -1444 | J22: 1000 | K22: USD | L22: =I22*J22/1000 -> -1444 | M22: =G22/3 -> 2 | N22: =-L22/M22 -> 722 | Q22: n/a: no Q1 10-Q (semi-annual/6-K filer) | T22: =IF(G22=3,-L22,IF(ISNUMBER(O22),-(L22-O22*P22/1000),IF(ISNUMBER(R22),-R22,"n/a"))) -> n/a | U22: 8152 | V22: 0 | W22: =(U22-V22)*J22/1000 -> 8152 | X22: =Inputs!$B$5 -> 1 | Y22: =N22*X22 -> 722 | Z22: 0001213900-26-087513 | AA22: https://www.sec.gov/Archives/edgar/data/1846715/000121390026087513/ea030083701ex99-1.htm | AB22: Semi-annual, so burn = H1 / 2.
A24: Check | B24: ODYS: computed Q2 (latest YTD - Q1 YTD) equals the Q2 figure the 10-Q reports directly | H24: =IF(ABS(-(L18-O18*P18/1000)-(-R18))<0.001,"PASS","FAIL") -> PASS

Sheet Sources
A1: Source map (all retrieved 2026-10-03)
A3: # | B3: Ticker | C3: Document | D3: Form | E3: Filed | F3: Accession | G3: Used for | H3: URL
A4: 1 | B4: ADXN | C4: adxn-20260630xex99d1.htm | D4: 6-K | E4: 2026-09-28 | F4: 0001104659-26-111142 | G4: Latest-period operating cash flow; period-end cash | H4: https://www.sec.gov/Archives/edgar/data/1574232/000110465926111142/adxn-20260630xex99d1.htm
A5: 2 | B5: AEON | C5: aeon-20260630x10q.htm | D5: 10-Q | E5: 2026-08-12 | F5: 0001837607-26-000062 | G5: Latest-period operating cash flow; period-end cash | H5: https://www.sec.gov/Archives/edgar/data/1837607/000183760726000062/aeon-20260630x10q.htm
A6: 3 | B6: AEON | C6: aeon-20260331x10q.htm | D6: 10-Q | E6: 2026-05-14 | F6: 0001837607-26-000042 | G6: Q1-2026 YTD operating cash flow (for latest discrete quarter) | H6: https://www.sec.gov/Archives/edgar/data/1837607/000183760726000042/aeon-20260331x10q.htm
A7: 4 | B7: ATCX | C7: ex99-1.htm | D7: 6-K | E7: 2026-07-31 | F7: 0001493152-26-035635 | G7: Latest-period operating cash flow; period-end cash | H7: https://www.sec.gov/Archives/edgar/data/1684688/000149315226035635/ex99-1.htm
A8: 5 | B8: CDIO | C8: cdio_10q-063026.htm | D8: 10-Q | E8: 2026-08-07 | F8: 0001079973-26-001016 | G8: Latest-period operating cash flow; period-end cash | H8: https://www.sec.gov/Archives/edgar/data/1870144/000107997326001016/cdio_10q-063026.htm
A9: 6 | B9: CDIO | C9: cdio_10q-033126.htm | D9: 10-Q | E9: 2026-05-15 | F9: 0001553350-26-000089 | G9: Q1-2026 YTD operating cash flow (for latest discrete quarter) | H9: https://www.sec.gov/Archives/edgar/data/1870144/000155335026000089/cdio_10q-033126.htm
A10: 7 | B10: EVGN | C10: exhibit_99-1.htm | D10: 6-K | E10: 2026-09-28 | F10: 0001178913-26-004636 | G10: Latest-period operating cash flow; period-end cash | H10: https://www.sec.gov/Archives/edgar/data/1574565/000117891326004636/exhibit_99-1.htm
A11: 8 | B11: EVGN | C11: exhibit_99-1.htm | D11: 6-K | E11: 2026-08-18 | F11: 0001178913-26-004174 | G11: Q2-2026 three-month operating cash flow (press release) | H11: https://www.sec.gov/Archives/edgar/data/1574565/000117891326004174/exhibit_99-1.htm
A12: 9 | B12: INTZ | C12: intrusion_i10q-063026.htm | D12: 10-Q | E12: 2026-08-11 | F12: 0001683168-26-006209 | G12: Latest-period operating cash flow; period-end cash | H12: https://www.sec.gov/Archives/edgar/data/736012/000168316826006209/intrusion_i10q-063026.htm
A13: 10 | B13: INTZ | C13: intrusion_i10q-033126.htm | D13: 10-Q | E13: 2026-05-14 | F13: 0001683168-26-003931 | G13: Q1-2026 YTD operating cash flow (for latest discrete quarter) | H13: https://www.sec.gov/Archives/edgar/data/736012/000168316826003931/intrusion_i10q-033126.htm
A14: 11 | B14: KAPA | C14: form10-q.htm | D14: 10-Q | E14: 2026-08-12 | F14: 0001493152-26-037355 | G14: Latest-period operating cash flow; period-end cash | H14: https://www.sec.gov/Archives/edgar/data/1962011/000149315226037355/form10-q.htm
A15: 12 | B15: KAPA | C15: form10-q.htm | D15: 10-Q | E15: 2026-05-13 | F15: 0001493152-26-022796 | G15: Q1-2026 YTD operating cash flow (for latest discrete quarter) | H15: https://www.sec.gov/Archives/edgar/data/1962011/000149315226022796/form10-q.htm
... A36: 33 | B36: All | C36: Filing histories (submissions API) | D36: SEC | E36: n/a | F36: n/a | G36: Identifying each company's latest periodic filing | H36: https://data.sec.gov/submissions/CIK##########.json

Sheet Method & Flags
A1: Method
A2: 1. For each ticker, mapped ticker to CIK using SEC company_tickers.json, then used the EDGAR submissions API to find the latest periodic report: 10-Q for U.S. filers, or the interim-financial-statements 6-K for foreign private issuers (period ending 2026-06-30).
A3: 2. Took "net cash used in operating activities" (the filing's own line label is shown on the Detail sheet) from the cash flow statement in that document. Each value was cross-checked against the filing's XBRL instance; WAVE does not tag this line in XBRL, so it was verified by re-adding the statement's line items (sum = 1,444).
A4: 3. Burn Rate ($K / qtr) = -(YTD operating cash flow) / (months in period / 3). For 6-month YTD statements this equals H1 / 2.
A5: 4. Latest discrete quarter ($K) = -(latest YTD - Q1 YTD from the prior 10-Q). EVGN: three-month figure from its Q2-2026 results release. ODYS: the 10-Q reports the three-month figure itself, and it matches the subtraction.
A6: 5. Total operating cash flow is used, including discontinued operations where present (EVGN, NSRX), because it is the cash actually spent. Capex and other investing outflows are excluded.
A8: Flags to review before you rely on this
A9: A. Mixed period types: 11 companies are true 10-Q filers. 7 (ADXN, ATCX, EVGN, MYND, NCEL, NSRX, WAVE) are foreign private issuers that report only half-year cash flows, so their Burn Rate is an H1 average, not a discrete quarter.
A10: B. Average and latest quarter diverge materially for TPST (5,189 avg vs 2,779 latest qtr), INTZ (2,706 vs 3,590), KPRX (2,527 vs 1,892), QNRX (4,007 vs 3,144), AEON (3,167 vs 3,698), LINK (415 vs 286), EVGN (2,464 vs 1,974). Choose the column that fits your use.
A11: C. OPTT's fiscal year ends April 30. Its latest 10-Q covers May-Jul 2026, one month later than everyone else's Jan-Jun period.
A12: D. ADXN is in CHF, not USD, for both Position and Burn Rate. The USD translation uses an FMP-sourced H1-2026 average rate (Inputs sheet).
A13: E. Position = cash & cash equivalents only. KPRX ($9.76M short-term investments), QNRX ($6.95M investments) and NSRX ($4.0M short-term deposit) hold extra liquidity outside that figure, so cash / burn understates their runway.
... A16: H. Not verified or not available: no discrete Q2 cash flow exists for ADXN, ATCX, MYND, NCEL, NSRX or WAVE in their filings. The FX rate comes from a third-party data feed (FMP), not an official central-bank fixing.
